[
  {
    "id": "kaushan-dey",
    "name": "Kaushan Dey",
    "year": 2024,
    "image": null,
    "email": null,
    "linkedin": null,
    "instagram": null,
    "history": [
      {
        "year": 2024,
        "departments": [
          "advisors"
        ],
        "roles": [
          {
            "dept": "advisors",
            "title": "Advisor"
          }
        ]
      }
    ]
  },
  {
    "id": "aman-yadav",
    "name": "Aman Yadav",
    "year": 2024,
    "image": null,
    "email": null,
    "linkedin": null,
    "instagram": null,
    "history": [
      {
        "year": 2024,
        "departments": [
          "advisors"
        ],
        "roles": [
          {
            "dept": "advisors",
            "title": "Advisor"
          }
        ]
      }
    ]
  },
  {
    "id": "aromal-s-ram",
    "name": "Aromal S Ram",
    "year": 2024,
    "image": null,
    "email": null,
    "linkedin": null,
    "instagram": null,
    "history": [
      {
        "year": 2024,
        "departments": [
          "former_leadership",
          "advisors"
        ],
        "roles": [
          {
            "dept": "former_leadership",
            "title": "Former Vice Captain"
          },
          {
            "dept": "advisors",
            "title": "Advisor"
          }
        ]
      }
    ]
  },
  {
    "id": "gudiwada-kartheek",
    "name": "Gudiwada Kartheek",
    "year": 2024,
    "image": null,
    "email": null,
    "linkedin": null,
    "instagram": null,
    "history": [
      {
        "year": 2024,
        "departments": [
          "advisors"
        ],
        "roles": [
          {
            "dept": "advisors",
            "title": "Advisor"
          }
        ]
      }
    ]
  },
  {
    "id": "jonathan-thomas-john",
    "name": "Jonathan Thomas John",
    "year": 2024,
    "image": null,
    "email": null,
    "linkedin": null,
    "instagram": null,
    "history": [
      {
        "year": 2024,
        "departments": [
          "advisors"
        ],
        "roles": [
          {
            "dept": "advisors",
            "title": "Advisor"
          }
        ]
      }
    ]
  },
  {
    "id": "roma-singh",
    "name": "Roma Singh",
    "year": 2024,
    "image": null,
    "email": null,
    "linkedin": null,
    "instagram": null,
    "history": [
      {
        "year": 2024,
        "departments": [
          "advisors"
        ],
        "roles": [
          {
            "dept": "advisors",
            "title": "Advisor"
          }
        ]
      }
    ]
  },
  {
    "id": "joy-vithyathil",
    "name": "Joy Vithyathil",
    "year": 2024,
    "image": null,
    "email": null,
    "linkedin": null,
    "instagram": null,
    "history": [
      {
        "year": 2024,
        "departments": [
          "advisors"
        ],
        "roles": [
          {
            "dept": "advisors",
            "title": "Advisor"
          }
        ]
      }
    ]
  },
  {
    "id": "shruti-sinha",
    "name": "Shruti Sinha",
    "year": 2024,
    "image": null,
    "email": null,
    "linkedin": null,
    "instagram": null,
    "history": [
      {
        "year": 2024,
        "departments": [
          "advisors"
        ],
        "roles": [
          {
            "dept": "advisors",
            "title": "Advisor"
          }
        ]
      }
    ]
  },
  {
    "id": "nitish-kumar",
    "name": "Nitish Kumar",
    "year": 2024,
    "image": null,
    "email": null,
    "linkedin": null,
    "instagram": null,
    "history": [
      {
        "year": 2024,
        "departments": [
          "former_leadership",
          "advisors"
        ],
        "roles": [
          {
            "dept": "former_leadership",
            "title": "Former Operations Head"
          },
          {
            "dept": "advisors",
            "title": "Advisor"
          }
        ]
      }
    ]
  },
  {
    "id": "om-shrivastava",
    "name": "Om Shrivastava",
    "year": 2024,
    "image": null,
    "email": null,
    "linkedin": null,
    "instagram": null,
    "history": [
      {
        "year": 2024,
        "departments": [
          "former_leadership",
          "advisors"
        ],
        "roles": [
          {
            "dept": "former_leadership",
            "title": "Former Captain"
          },
          {
            "dept": "advisors",
            "title": "Advisor"
          }
        ]
      }
    ]
  },
  {
    "id": "sangeeth-m-ajith",
    "name": "Sangeeth M Ajith",
    "year": 2024,
    "image": null,
    "email": "mailto:sangeeth.m.ajith@mechismu.com",
    "linkedin": "https://www.linkedin.com/in/sangeethmajith/",
    "instagram": null,
    "history": [
      {
        "year": 2024,
        "departments": [
          "leadership",
          "structures"
        ],
        "roles": [
          {
            "dept": "leadership",
            "title": "Team Captain"
          },
          {
            "dept": "structures",
            "title": "Structures Head"
          }
        ]
      }
    ]
  },
  {
    "id": "maninder-singh",
    "name": "Maninder Singh",
    "year": 2024,
    "image": null,
    "email": "mailto:maninder.singh@mechismu.com",
    "linkedin": "https://www.linkedin.com/in/mrdimara/",
    "instagram": null,
    "history": [
      {
        "year": 2024,
        "departments": [
          "leadership",
          "lv"
        ],
        "roles": [
          {
            "dept": "leadership",
            "title": "Vice Captain"
          },
          {
            "dept": "lv",
            "title": "LV Head"
          }
        ]
      }
    ]
  },
  {
    "id": "sahil-kumar",
    "name": "Sahil Kumar",
    "year": 2024,
    "image": null,
    "email": "mailto:sahil.kumar@mechismu.com",
    "linkedin": "https://www.linkedin.com/in/sahil-kumar-0b0784287/",
    "instagram": null,
    "history": [
      {
        "year": 2024,
        "departments": [
          "hv",
          "leadership"
        ],
        "roles": [
          {
            "dept": "hv",
            "title": "HV Head"
          },
          {
            "dept": "leadership",
            "title": "HV Lead "
          }
        ]
      }
    ]
  },
  {
    "id": "arindam-jha",
    "name": "Arindam Jha",
    "year": 2024,
    "image": null,
    "email": "mailto:arindam-jha@mechismu.com",
    "linkedin": "https://www.linkedin.com/in/arindamjha/",
    "instagram": null,
    "history": [
      {
        "year": 2024,
        "departments": [
          "vd",
          "leadership"
        ],
        "roles": [
          {
            "dept": "vd",
            "title": "Vehicle Dynamics Head"
          },
          {
            "dept": "leadership",
            "title": "VD Lead"
          }
        ]
      }
    ]
  },
  {
    "id": "yash-rao",
    "name": "Yash Rao",
    "year": 2024,
    "image": null,
    "email": "mailto:yash.rao@mechismu.com",
    "linkedin": "https://www.linkedin.com/in/yash-rao-71820a287/",
    "instagram": null,
    "history": [
      {
        "year": 2024,
        "departments": [
          "vd",
          "leadership"
        ],
        "roles": [
          {
            "dept": "vd",
            "title": "Manufacturing Head"
          },
          {
            "dept": "leadership",
            "title": "Manufacturing Lead"
          }
        ]
      }
    ]
  },
  {
    "id": "justin-george",
    "name": "Justin George",
    "year": 2024,
    "image": null,
    "email": "mailto:justin.george@mechismu.com",
    "linkedin": "https://www.linkedin.com/in/jstingeorg/",
    "instagram": null,
    "history": [
      {
        "year": 2024,
        "departments": [
          "ops",
          "leadership"
        ],
        "roles": [
          {
            "dept": "ops",
            "title": "Operations Head"
          },
          {
            "dept": "leadership",
            "title": "Operations Lead"
          }
        ]
      }
    ]
  },
  {
    "id": "debasish-das",
    "name": "Debasish Das",
    "image": null,
    "email": null,
    "linkedin": null,
    "instagram": null,
    "history": [
      {
        "year": 2024,
        "departments": [
          "vd"
        ],
        "roles": [
          {
            "dept": "vd",
            "title": "Vehicle Dynamics"
          }
        ]
      }
    ]
  },
  {
    "id": "nithin-gowda",
    "name": "Nithin Gowda",
    "image": null,
    "email": null,
    "linkedin": null,
    "instagram": null,
    "history": [
      {
        "year": 2024,
        "departments": [
          "vd"
        ],
        "roles": [
          {
            "dept": "vd",
            "title": "Vehicle Dynamics"
          }
        ]
      }
    ]
  },
  {
    "id": "sidharth-patel",
    "name": "Sidharth Patel",
    "image": null,
    "email": null,
    "linkedin": null,
    "instagram": null,
    "history": [
      {
        "year": 2024,
        "departments": [
          "vd"
        ],
        "roles": [
          {
            "dept": "vd",
            "title": "Vehicle Dynamics"
          }
        ]
      }
    ]
  },
  {
    "id": "v.-v.-m.-sai-nandan",
    "name": "V.V.M.Sai Nandan",
    "image": null,
    "email": null,
    "linkedin": null,
    "instagram": null,
    "history": [
      {
        "year": 2024,
        "departments": [
          "vd"
        ],
        "roles": [
          {
            "dept": "vd",
            "title": "Vehicle Dynamics"
          }
        ]
      }
    ]
  },
  {
    "id": "ayush-kumar-verma",
    "name": "Ayush Kumar Verma",
    "image": null,
    "email": null,
    "linkedin": null,
    "instagram": null,
    "history": [
      {
        "year": 2024,
        "departments": [
          "vd"
        ],
        "roles": [
          {
            "dept": "vd",
            "title": "Vehicle Dynamics"
          }
        ]
      }
    ]
  },
  {
    "id": "vansh-motghare",
    "name": "Vansh Motghare",
    "image": null,
    "email": null,
    "linkedin": null,
    "instagram": null,
    "history": [
      {
        "year": 2024,
        "departments": [
          "vd"
        ],
        "roles": [
          {
            "dept": "vd",
            "title": "Vehicle Dynamics"
          }
        ]
      }
    ]
  },
  {
    "id": "priyam-ghosh",
    "name": "Priyam Ghosh",
    "image": null,
    "email": null,
    "linkedin": null,
    "instagram": null,
    "history": [
      {
        "year": 2024,
        "departments": [
          "vd"
        ],
        "roles": [
          {
            "dept": "vd",
            "title": "Vehicle Dynamics"
          }
        ]
      }
    ]
  },
  {
    "id": "verma-aashu",
    "name": "Verma Aashu",
    "image": null,
    "email": null,
    "linkedin": null,
    "instagram": null,
    "history": [
      {
        "year": 2024,
        "departments": [
          "vd"
        ],
        "roles": [
          {
            "dept": "vd",
            "title": "Vehicle Dynamics"
          }
        ]
      }
    ]
  },
  {
    "id": "saaketharam-kristipati",
    "name": "Saaketharam Kristipati",
    "image": null,
    "email": null,
    "linkedin": null,
    "instagram": null,
    "history": [
      {
        "year": 2024,
        "departments": [
          "vd"
        ],
        "roles": [
          {
            "dept": "vd",
            "title": "Vehicle Dynamics"
          }
        ]
      }
    ]
  },
  {
    "id": "debjyoti-banerjee",
    "name": "Debjyoti Banerjee",
    "image": null,
    "email": null,
    "linkedin": null,
    "instagram": null,
    "history": [
      {
        "year": 2024,
        "departments": [
          "hv"
        ],
        "roles": [
          {
            "dept": "hv",
            "title": "HV Powertrain "
          }
        ]
      }
    ]
  },
  {
    "id": "hemang-choubey",
    "name": "Hemang Choubey",
    "image": null,
    "email": null,
    "linkedin": null,
    "instagram": null,
    "history": [
      {
        "year": 2024,
        "departments": [
          "hv"
        ],
        "roles": [
          {
            "dept": "hv",
            "title": "HV Powertrain "
          }
        ]
      }
    ]
  },
  {
    "id": "asu-kumar",
    "name": "Asu Kumar",
    "image": null,
    "email": null,
    "linkedin": null,
    "instagram": null,
    "history": [
      {
        "year": 2024,
        "departments": [
          "hv"
        ],
        "roles": [
          {
            "dept": "hv",
            "title": "HV Powertrain "
          }
        ]
      }
    ]
  },
  {
    "id": "abhimamyu-kumar",
    "name": "Abhimamyu Kumar",
    "image": null,
    "email": null,
    "linkedin": null,
    "instagram": null,
    "history": [
      {
        "year": 2024,
        "departments": [
          "hv"
        ],
        "roles": [
          {
            "dept": "hv",
            "title": "HV Powertrain "
          }
        ]
      }
    ]
  },
  {
    "id": "anurag-patel",
    "name": "Anurag Patel",
    "image": null,
    "email": null,
    "linkedin": null,
    "instagram": null,
    "history": [
      {
        "year": 2024,
        "departments": [
          "lv",
          "ops"
        ],
        "roles": [
          {
            "dept": "lv",
            "title": "LV Electronics"
          },
          {
            "dept": "ops",
            "title": "Operations"
          }
        ]
      }
    ]
  },
  {
    "id": "t-v-saravanesh",
    "name": "T.V.Saravanesh",
    "image": null,
    "email": null,
    "linkedin": null,
    "instagram": null,
    "history": [
      {
        "year": 2024,
        "departments": [
          "lv"
        ],
        "roles": [
          {
            "dept": "lv",
            "title": "LV Electronics"
          }
        ]
      }
    ]
  },
  {
    "id": "sukanya",
    "name": "Sukanya",
    "image": null,
    "email": null,
    "linkedin": null,
    "instagram": null,
    "history": [
      {
        "year": 2024,
        "departments": [
          "lv"
        ],
        "roles": [
          {
            "dept": "lv",
            "title": "LV Electronics"
          }
        ]
      }
    ]
  },
  {
    "id": "kartikey-shukla",
    "name": "Kartikey Shukla",
    "image": null,
    "email": null,
    "linkedin": null,
    "instagram": null,
    "history": [
      {
        "year": 2024,
        "departments": [
          "lv"
        ],
        "roles": [
          {
            "dept": "lv",
            "title": "LV Electronics"
          }
        ]
      }
    ]
  },
  {
    "id": "poladi-hamsini",
    "name": "Poladi Hamsini",
    "image": null,
    "email": null,
    "linkedin": null,
    "instagram": null,
    "history": [
      {
        "year": 2024,
        "departments": [
          "lv"
        ],
        "roles": [
          {
            "dept": "lv",
            "title": "LV Electronics"
          }
        ]
      }
    ]
  },
  {
    "id": "subrat-panda",
    "name": "Subrat Panda",
    "image": null,
    "email": null,
    "linkedin": null,
    "instagram": null,
    "history": [
      {
        "year": 2024,
        "departments": [
          "lv"
        ],
        "roles": [
          {
            "dept": "lv",
            "title": "LV Electronics"
          }
        ]
      }
    ]
  },
  {
    "id": "aditya-kumar",
    "name": "Aditya Kumar",
    "image": null,
    "email": null,
    "linkedin": null,
    "instagram": null,
    "history": [
      {
        "year": 2024,
        "departments": [
          "structures"
        ],
        "roles": [
          {
            "dept": "structures",
            "title": "Structures"
          }
        ]
      }
    ]
  },
  {
    "id": "surup-kumar-singh",
    "name": "Surup Kumar Singh",
    "image": null,
    "email": null,
    "linkedin": null,
    "instagram": null,
    "history": [
      {
        "year": 2024,
        "departments": [
          "structures"
        ],
        "roles": [
          {
            "dept": "structures",
            "title": "Structures"
          }
        ]
      }
    ]
  },
  {
    "id": "manas-dubey",
    "name": "Manas Dubey",
    "image": null,
    "email": null,
    "linkedin": null,
    "instagram": null,
    "history": [
      {
        "year": 2024,
        "departments": [
          "structures"
        ],
        "roles": [
          {
            "dept": "structures",
            "title": "Structures"
          }
        ]
      }
    ]
  },
  {
    "id": "sudhanya-pati",
    "name": "Sudhanya Pati",
    "image": null,
    "email": null,
    "linkedin": null,
    "instagram": null,
    "history": [
      {
        "year": 2024,
        "departments": [
          "structures"
        ],
        "roles": [
          {
            "dept": "structures",
            "title": "Structures"
          }
        ]
      }
    ]
  },
  {
    "id": "mahi-rathore",
    "name": "Mahi Rathore",
    "image": null,
    "email": null,
    "linkedin": null,
    "instagram": null,
    "history": [
      {
        "year": 2024,
        "departments": [
          "structures"
        ],
        "roles": [
          {
            "dept": "structures",
            "title": "Structures"
          }
        ]
      }
    ]
  }
]